Metadata-Version: 2.1
Name: aflevering3-tree
Version: 0.0.3
Summary: A collection of functions from Aflevering 3
Home-page: UNKNOWN
Author: Christopher L. Kristiansen
Author-email: Christopher@kristiansenz.com
License: MIT
Platform: UNKNOWN
Classifier: Development Status :: 5 - Production/Stable
Classifier: Intended Audience :: Education
Classifier: Operating System :: Microsoft :: Windows :: Windows 10
Classifier: License :: OSI Approved :: MIT License
Classifier: Programming Language :: Python :: 3
License-File: LICENSE.txt
